mix_voice/__init__.py
mix_voice-0.1.dist-info/METADATA
mix_voice-0.1.dist-info/WHEEL
mix_voice-0.1.dist-info/license
mix_voice-0.1.dist-info/top_level.txt
mix_voice-0.1.dist-info/RECORD
