Metadata-Version: 2.1
Name: mix-voice
Version: 0.1
Summary: This is a talk module. Check the long description for more info.
Home-page: UNKNOWN
Author: Nishant Deb
Author-email: debnishant830@gmail.com
License: ./license
Keywords: talk,talk module,TALK MODULE,Talk Module,speaking,speak,module,MODULE,Module
Platform: UNKNOWN
License-File: license
Requires-Dist: pyttsx3
Requires-Dist: speechRecognition
